ksei/__init__.py
ksei/client.py
ksei/utils.py
ksei-0.1.2.dist-info/WHEEL
ksei-0.1.2.dist-info/entry_points.txt
ksei-0.1.2.dist-info/METADATA
ksei-0.1.2.dist-info/RECORD
