Metadata-Version: 2.3
Name: ksei
Version: 0.1.2
Summary: A Python client for interacting with the KSEI (PT Kustodian Sentral Efek Indonesia) API
Keywords: ksei,indonesia,securities,depository,ksei,finance,indonesian-capital-market
Author: Your Name
Author-email: Your Name <your.email@example.com>
License: MIT License
Classifier: Development Status :: 4 - Beta
Classifier: Intended Audience :: Financial and Insurance Industry
Classifier: License :: OSI Approved :: MIT License
Classifier: Operating System :: OS Independent
Classifier: Programming Language :: Python :: 3
Classifier: Programming Language :: Python :: 3.12
Classifier: Programming Language :: Python :: 3.13
Classifier: Programming Language :: Python :: 3.14
Classifier: Programming Language :: Python :: 3 :: Only
Classifier: Topic :: Office/Business :: Financial :: Investment
Classifier: Topic :: Software Development :: Libraries :: Python Modules
Classifier: Topic :: Office/Business :: Financial
Requires-Dist: fake-useragent>=2.2.0
Requires-Dist: pyjwt>=2.10.1
Requires-Dist: httpx>=0.27.0
Maintainer: Your Name
Maintainer-email: Your Name <your.email@example.com>
Requires-Python: >=3.12
Project-URL: Bug Tracker, https://github.com/nichsedge/ksei/issues
Project-URL: Documentation, https://github.com/nichsedge/ksei#readme
Project-URL: Homepage, https://github.com/nichsedge/ksei
Project-URL: Repository, https://github.com/nichsedge/ksei.git
